girder_gravatar/__init__.py
girder_gravatar/settings.py
girder_gravatar/web_client/dist/girder-plugin-gravatar.umd.cjs
girder_gravatar-5.0.0a14.dev27.dist-info/METADATA
girder_gravatar-5.0.0a14.dev27.dist-info/WHEEL
girder_gravatar-5.0.0a14.dev27.dist-info/entry_points.txt
girder_gravatar-5.0.0a14.dev27.dist-info/top_level.txt
girder_gravatar-5.0.0a14.dev27.dist-info/RECORD
